HomeWorks/Lab1/tern/ternary_logic.v
// module ternary_min(a0, a1, b0, b1, out0, out1);
//   input a0, a1, b0, b1;
//   output out0, out1;

// endmodule

module ternary_max(a0, a1, b0, b1, out0, out1);
  input wire a0, a1, b0, b1;
  output wire out0, out1;

  wire w1, w2;
  or_switch my_or1(a0, b0, out0);
  or_switch my_or2(a1, b1, w1);
  xor_switch my_xor(out0, w1, w2);
  and_switch my_and(w1, w2, out1);

endmodule

// module ternary_any(a0, a1, b0, b1, out0, out1);
//   input a0, a1, b0, b1;
//   output out0, out1;

// endmodule

module ternary_consensus(a0, a1, b0, b1, out0, out1);
  input wire a0, a1, b0, b1;
  output out0, out1;

  wire w1, w2;
  and_switch my_and(a0, b0, out0);
  or_switch my_or(a1, b1, w1);
  xor_switch my_xor(a0, b0, w2);
  or_switch res_or(w1, w2, out1);
  

endmodule


// Primitives

module not_switch (in, out);
    input wire in;
    output wire out;

    supply0 ground;
    supply1 power;

    pmos p1(out, power, in);
    nmos n1(out, ground, in);
    
endmodule


module nor_switch (a, b, out);
    input wire a, b;
    output wire out;
    wire w;

    supply0 ground;
    supply1 power;

    pmos p1(w, power, b);
    pmos p2(out, w, a);

    nmos n1(out, ground, a);
    nmos n2(out, ground, b);

endmodule


module nand_switch (a, b, out);
    input wire a, b;
    output wire out;
    wire w;

    supply0 ground;
    supply1 power;

    nmos n1(w, ground, b);
    nmos n2(out, w, a);

    pmos p1(out, power, a);
    pmos p2(out, power, b);

endmodule


module and_switch (a, b, out);
    input wire a, b;
    output wire out;

    wire w;
    nand_switch my_nand (a, b, w);
    not_switch my_not (w, out);

endmodule

module or_switch (a, b, out);
    input wire a, b;
    output wire out;

    wire w;
    nor_switch my_nor (a, b, w);
    not_switch my_not (w, out);

endmodule


module xor_switch (a, b, out);
    input wire a, b, a2, b2;
    output wire out;

    wire w1, w2;

    not_switch not_a(a, a2);
    not_switch not_b(b, b2);

    and_switch a_not_b(a, b2, w1);
    and_switch b_not_a(a2, b, w2);

    or_switch my_xor(w1, w2, out);

endmodule

HomeWorks/Lab1/tern/test_consensus.v
`include "ternary_logic.v"

module test_consensus();
    reg a0, a1, b0, b1;
    wire out0, out1;
    

    ternary_consensus my_consensus(a0, a1, b0, b1, out0, out1);
    
    // initial begin
    //    $dumpfile("./dumpCons.vcd");
    //    $dumpvars; 
    // end

    initial begin
        $monitor("Input a: %b%b, Input b: %b%b Output: %b%b", a0, a1, b0, b1, out0, out1);
        a0 = 0; a1 = 0; b0 = 0; b1 = 0;
        #5 a0 = 0; a1 = 0; b0 = 0; b1 = 1;
        #5 a0 = 0; a1 = 0; b0 = 1; b1 = 0;
        #5 a0 = 0; a1 = 1; b0 = 0; b1 = 0;
        #5 a0 = 0; a1 = 1; b0 = 0; b1 = 1;
        #5 a0 = 0; a1 = 1; b0 = 1; b1 = 0;
        #5 a0 = 1; a1 = 0; b0 = 0; b1 = 0;
        #5 a0 = 1; a1 = 0; b0 = 0; b1 = 1;
        #5 a0 = 1; a1 = 0; b0 = 1; b1 = 0;
    end

endmodule

HomeWorks/Lab1/tern/dumpCons.vcd
$date
	Tue May  2 12:10:55 2023
$end
$version
	Icarus Verilog
$end
$timescale
	1s
$end
$scope module test_consensus $end
$var wire 1 ! out0 $end
$var wire 1 " out1 $end
$var reg 1 # a0 $end
$var reg 1 $ a1 $end
$var reg 1 % b0 $end
$var reg 1 & b1 $end
$scope module my_consensus $end
$var wire 1 # a0 $end
$var wire 1 $ a1 $end
$var wire 1 % b0 $end
$var wire 1 & b1 $end
$var wire 1 ! out0 $end
$var wire 1 " out1 $end
$var wire 1 ' w1 $end
$var wire 1 ( w2 $end
$scope module my_and $end
$var wire 1 # a $end
$var wire 1 % b $end
$var wire 1 ! out $end
$var wire 1 ) w $end
$scope module my_nand $end
$var wire 1 # a $end
$var wire 1 % b $end
$var wire 1 * ground $end
$var wire 1 ) out $end
$var wire 1 + power $end
$var wire 1 , w $end
$upscope $end
$scope module my_not $end
$var wire 1 - ground $end
$var wire 1 ) in $end
$var wire 1 ! out $end
$var wire 1 . power $end
$upscope $end
$upscope $end
$scope module my_or $end
$var wire 1 $ a $end
$var wire 1 & b $end
$var wire 1 ' out $end
$var wire 1 / w $end
$scope module my_nor $end
$var wire 1 $ a $end
$var wire 1 & b $end
$var wire 1 0 ground $end
$var wire 1 / out $end
$var wire 1 1 power $end
$var wire 1 2 w $end
$upscope $end
$scope module my_not $end
$var wire 1 3 ground $end
$var wire 1 / in $end
$var wire 1 ' out $end
$var wire 1 4 power $end
$upscope $end
$upscope $end
$scope module my_xor $end
$var wire 1 # a $end
$var wire 1 5 a2 $end
$var wire 1 % b $end
$var wire 1 6 b2 $end
$var wire 1 ( out $end
$var wire 1 7 w1 $end
$var wire 1 8 w2 $end
$scope module a_not_b $end
$var wire 1 # a $end
$var wire 1 6 b $end
$var wire 1 7 out $end
$var wire 1 9 w $end
$scope module my_nand $end
$var wire 1 # a $end
$var wire 1 6 b $end
$var wire 1 : ground $end
$var wire 1 9 out $end
$var wire 1 ; power $end
$var wire 1 < w $end
$upscope $end
$scope module my_not $end
$var wire 1 = ground $end
$var wire 1 9 in $end
$var wire 1 7 out $end
$var wire 1 > power $end
$upscope $end
$upscope $end
$scope module b_not_a $end
$var wire 1 5 a $end
$var wire 1 % b $end
$var wire 1 8 out $end
$var wire 1 ? w $end
$scope module my_nand $end
$var wire 1 5 a $end
$var wire 1 % b $end
$var wire 1 @ ground $end
$var wire 1 ? out $end
$var wire 1 A power $end
$var wire 1 B w $end
$upscope $end
$scope module my_not $end
$var wire 1 C ground $end
$var wire 1 ? in $end
$var wire 1 8 out $end
$var wire 1 D power $end
$upscope $end
$upscope $end
$scope module my_xor $end
$var wire 1 7 a $end
$var wire 1 8 b $end
$var wire 1 ( out $end
$var wire 1 E w $end
$scope module my_nor $end
$var wire 1 7 a $end
$var wire 1 8 b $end
$var wire 1 F ground $end
$var wire 1 E out $end
$var wire 1 G power $end
$var wire 1 H w $end
$upscope $end
$scope module my_not $end
$var wire 1 I ground $end
$var wire 1 E in $end
$var wire 1 ( out $end
$var wire 1 J power $end
$upscope $end
$upscope $end
$scope module not_a $end
$var wire 1 K ground $end
$var wire 1 # in $end
$var wire 1 5 out $end
$var wire 1 L power $end
$upscope $end
$scope module not_b $end
$var wire 1 M ground $end
$var wire 1 % in $end
$var wire 1 6 out $end
$var wire 1 N power $end
$upscope $end
$upscope $end
$scope module res_or $end
$var wire 1 ' a $end
$var wire 1 ( b $end
$var wire 1 " out $end
$var wire 1 O w $end
$scope module my_nor $end
$var wire 1 ' a $end
$var wire 1 ( b $end
$var wire 1 P ground $end
$var wire 1 O out $end
$var wire 1 Q power $end
$var wire 1 R w $end
$upscope $end
$scope module my_not $end
$var wire 1 S ground $end
$var wire 1 O in $end
$var wire 1 " out $end
$var wire 1 T power $end
$upscope $end
$upscope $end
$upscope $end
$upscope $end
$enddefinitions $end
#0
$dumpvars
1T
0S
1R
1Q
0P
1O
1N
0M
1L
0K
1J
0I
1H
1G
0F
1E
1D
0C
zB
1A
0@
1?
1>
0=
0<
1;
0:
19
08
07
16
15
14
03
12
11
00
1/
1.
0-
z,
1+
0*
1)
0(
0'
0&
0%
0$
0#
0"
0!
$end
#5
z2
1"
0O
1'
0/
1&
#10
12
0'
1/
0&
0,
0B
zH
zR
1(
0E
18
0?
z<
06
1%
#15
z,
zB
1H
1R
0(
1E
08
1?
0<
16
0%
1'
0/
1$
#20
z2
1&
#25
12
0&
0,
0B
zH
zR
1(
0E
18
0?
z<
06
1%
#30
z,
zB
0<
17
09
16
0%
1"
0O
0'
1/
0$
0!
1)
1H
zR
1(
0E
08
1?
05
1#
#35
z2
1'
0/
1&
#40
12
0"
1O
0'
1/
0&
0,
1!
0)
0B
z<
1R
0(
1E
07
19
06
1%
